apiTestHttp/__init__.py
apiTestHttp/apiTestMain.py
apiTestHttp/apitest.py
apiTestHttp/testCasesRun.py
apiTestHttp/uitest.py
apitestbasiclib/__init__.py
apitestbasiclib/apibasic.py
apitestbasiclib/apirequest.py
apitestbasiclib/apitestlogic.py
apitestbasiclib/dbutils.py
apitestbasiclib/filetools.py
apitestbasiclib/jsoncompare.py
apitestbasiclib/log.py
apiTestHttp-0.0.14.dist-info/METADATA
apiTestHttp-0.0.14.dist-info/WHEEL
apiTestHttp-0.0.14.dist-info/entry_points.txt
apiTestHttp-0.0.14.dist-info/top_level.txt
apiTestHttp-0.0.14.dist-info/RECORD
